README.md
setup.py
dbx/__init__.py
dbx/__main__.py
dbx/dbx.py
py_dbx.egg-info/PKG-INFO
py_dbx.egg-info/SOURCES.txt
py_dbx.egg-info/dependency_links.txt
py_dbx.egg-info/entry_points.txt
py_dbx.egg-info/requires.txt
py_dbx.egg-info/top_level.txt