Metadata-Version: 2.1
Name: py-dbx
Version: 1.0.2
Summary: make jdbc calls in command line
Home-page: https://github.com/laowangv5/py-dbx
Author: Yonghang Wang
Author-email: wyhang@gmail.com
License: Apache 2
Keywords: jdbc,dbx
Platform: UNKNOWN
Classifier: License :: OSI Approved :: Apache Software License
